covar.pyx
setup.py
covar.egg-info/PKG-INFO
covar.egg-info/SOURCES.txt
covar.egg-info/dependency_links.txt
covar.egg-info/not-zip-safe
covar.egg-info/requires.txt
covar.egg-info/top_level.txt