Metadata-Version: 1.0
Name: covar
Version: 0.1
Summary: Shrinkage covariance estimator for python
Home-page: https://github.com/rmcgibbo/covar
Author: Robert T. McGibbon
Author-email: rmcgibbo@gmail.com
License: BSD
Platform: UNKNOWN
